LICENSE
README.md
setup.py
pythonasm/__init__.py
pythonasm/main.py
pythonasm_linhhanpy.egg-info/PKG-INFO
pythonasm_linhhanpy.egg-info/SOURCES.txt
pythonasm_linhhanpy.egg-info/dependency_links.txt
pythonasm_linhhanpy.egg-info/requires.txt
pythonasm_linhhanpy.egg-info/top_level.txt