Metadata-Version: 2.1
Name: pythonasm-linhhanpy
Version: 0.0.1
Summary: A Python library for ASM
Home-page: https://gitee.com/linhhpy/
Author: linhhanpy
Author-email: lhh_88888888@qq.com
Classifier: Programming Language :: Python :: 3
Classifier: License :: OSI Approved :: MIT License
Classifier: Operating System :: OS Independent
Requires-Python: >=3.6
License-File: LICENSE
Requires-Dist: re
Requires-Dist: os
